fsva/__init__.py
fsva/main.py
fsva/verification_target.py
fsva-1.1.0.dist-info/LICENSE
fsva-1.1.0.dist-info/METADATA
fsva-1.1.0.dist-info/WHEEL
fsva-1.1.0.dist-info/entry_points.txt
fsva-1.1.0.dist-info/top_level.txt
fsva-1.1.0.dist-info/RECORD
