Metadata-Version: 2.1
Name: fsva
Version: 1.1.0
Summary: fsva (FuseSoc Verification Automation)
Home-page: https://github.com/m-kru/fsva
Author: Michał Kruszewski
Author-email: mkru@protonmail.com
License: MIT
Keywords: verification,simulation,testbench,FuseSoc,VHDL,SystemVerilog,UVVM,OSVVM,GHDL,Questa,HDL,RTL,FPGA
Platform: UNKNOWN
Classifier: Topic :: Scientific/Engineering :: Electronic Design Automation (EDA)
Classifier: Topic :: Software Development :: Testing
Classifier: Topic :: Software Development :: Quality Assurance
Classifier: Topic :: Utilities
Classifier: Intended Audience :: End Users/Desktop
Classifier: License :: OSI Approved :: MIT License
License-File: LICENSE
Requires-Dist: fusesoc (>=1.9.1)
